pg_rollingwindow.py
setup.py
pg_rollingwindow.egg-info/PKG-INFO
pg_rollingwindow.egg-info/SOURCES.txt
pg_rollingwindow.egg-info/dependency_links.txt
pg_rollingwindow.egg-info/requires.txt
pg_rollingwindow.egg-info/top_level.txt