Metadata-Version: 1.0
Name: pg-rollingwindow
Version: 1.0
Summary: Manage partition tables in PostgreSQL
Home-page: https://github.com/ahammond/pg_rollingwindow
Author: Andrew Hammond
Author-email: andrew.george.hammond@gmail.com
License: UNKNOWN
Platform: UNKNOWN
